crystalyse_ai/__init__.py
crystalyse_ai/__main__.py
crystalyse_ai/cli.py
crystalyse_ai/config.py
crystalyse_ai/converters.py
crystalyse_ai/unified_cli.py
crystalyse_ai/agents/__init__.py
crystalyse_ai/agents/crystalyse_agent.py
crystalyse_ai/agents/mcp_utils.py
crystalyse_ai/agents/session_based_agent.py
crystalyse_ai/infrastructure/__init__.py
crystalyse_ai/infrastructure/mcp_connection_pool.py
crystalyse_ai/infrastructure/resilient_tool_caller.py
crystalyse_ai/infrastructure/session_manager.py
crystalyse_ai/mcp_servers/__init__.py
crystalyse_ai/mcp_servers/creative/__init__.py
crystalyse_ai/mcp_servers/creative/server.py
crystalyse_ai/mcp_servers/unified/__init__.py
crystalyse_ai/mcp_servers/unified/server.py
crystalyse_ai/mcp_servers/visualization/__init__.py
crystalyse_ai/mcp_servers/visualization/browser_pool.py
crystalyse_ai/mcp_servers/visualization/server.py
crystalyse_ai/mcp_servers/visualization/tools.py
crystalyse_ai/memory/__init__.py
crystalyse_ai/memory/cross_session_context.py
crystalyse_ai/memory/crystalyse_memory.py
crystalyse_ai/memory/discovery_cache.py
crystalyse_ai/memory/memory_tools.py
crystalyse_ai/memory/session_memory.py
crystalyse_ai/memory/user_memory.py
crystalyse_ai/output/__init__.py
crystalyse_ai/output/creative_formatter.py
crystalyse_ai/output/dual_formatter.py
crystalyse_ai/output/universal_cif_visualizer.py
crystalyse_ai/prompts/unified_agent_prompt.md
crystalyse_ai/tests/test_visualization.py
crystalyse_ai/tools/__init__.py
crystalyse_ai/tools/chemeleon.py
crystalyse_ai/tools/chemeleon_installer.py
crystalyse_ai/tools/dependency_checker.py
crystalyse_ai/tools/mace.py
crystalyse_ai/tools/smact.py
crystalyse_ai/tools/visualization.py
crystalyse_ai/ui/__init__.py
crystalyse_ai/ui/ascii_art.py
crystalyse_ai/ui/components.py
crystalyse_ai/ui/enhanced_cli.py
crystalyse_ai/ui/gradients.py
crystalyse_ai/ui/themes.py
crystalyse_ai/utils/__init__.py
crystalyse_ai/utils/chemistry.py
crystalyse_ai/utils/structure.py
crystalyse_ai-1.0.14.dist-info/METADATA
crystalyse_ai-1.0.14.dist-info/WHEEL
crystalyse_ai-1.0.14.dist-info/entry_points.txt
crystalyse_ai-1.0.14.dist-info/top_level.txt
crystalyse_ai-1.0.14.dist-info/RECORD
