Metadata-Version: 2.4
Name: crystalyse-ai
Version: 1.0.14
Summary: CrystaLyse.AI - Autonomous AI agents for accelerated inorganic materials design through natural language interfaces
Author: CrystaLyse.AI Development Team
Maintainer: CrystaLyse.AI Development Team
Project-URL: Homepage, https://github.com/ryannduma/CrystaLyse.AI
Project-URL: Documentation, https://crystalyse-ai.readthedocs.io/
Project-URL: Repository, https://github.com/ryannduma/CrystaLyse.AI.git
Project-URL: Issues, https://github.com/ryannduma/CrystaLyse.AI/issues
Project-URL: Changelog, https://github.com/ryannduma/CrystaLyse.AI/blob/main/CHANGELOG.md
Keywords: materials-design,crystal-structure-prediction,formation-energy,computational-materials-science,ai,chemistry,inorganic-materials,autonomous-agents
Classifier: Development Status :: 4 - Beta
Classifier: Intended Audience :: Science/Research
Classifier: Intended Audience :: Education
Classifier: License :: OSI Approved :: MIT License
Classifier: Operating System :: OS Independent
Classifier: Programming Language :: Python :: 3
Classifier: Programming Language :: Python :: 3.11
Classifier: Programming Language :: Python :: 3.12
Classifier: Topic :: Scientific/Engineering :: Chemistry
Classifier: Topic :: Scientific/Engineering :: Artificial Intelligence
Classifier: Topic :: Software Development :: Libraries :: Python Modules
Requires-Python: >=3.11
Requires-Dist: openai>=1.0.0
Requires-Dist: openai-agents>=0.0.16
Requires-Dist: rdkit>=2023.9.1
Requires-Dist: pymatgen>=2024.1.0
Requires-Dist: ase>=3.22.0
Requires-Dist: smact>=2.7.0
Requires-Dist: torch>=2.0.0
Requires-Dist: mace-torch>=0.3.4
Requires-Dist: gitpython>=3.1.0
Requires-Dist: fastmcp>=0.5.0
Requires-Dist: numpy>=1.24.0
Requires-Dist: pandas>=2.0.0
Requires-Dist: scipy>=1.11.0
Requires-Dist: typing-extensions>=4.5.0
Requires-Dist: pydantic>=2.0.0
Requires-Dist: click>=8.1.0
Requires-Dist: rich>=13.0.0
Requires-Dist: prompt-toolkit>=3.0.0
Requires-Dist: asyncio>=3.4.3
Requires-Dist: httpx>=0.24.0
Requires-Dist: websockets>=11.0.0
Requires-Dist: PyYAML>=6.0.0
Requires-Dist: toml>=0.10.0
Requires-Dist: python-dotenv>=1.0.0
Requires-Dist: uvicorn>=0.23.0
Requires-Dist: fastapi>=0.104.0
Requires-Dist: starlette>=0.27.0
Provides-Extra: visualization
Requires-Dist: matplotlib>=3.7.0; extra == "visualization"
Requires-Dist: plotly>=5.18.0; extra == "visualization"
Requires-Dist: py3Dmol>=2.0.4; extra == "visualization"
Requires-Dist: kaleido>=0.2.1; extra == "visualization"
Requires-Dist: pymatviz>=0.8.5; extra == "visualization"
Requires-Dist: seaborn>=0.12.0; extra == "visualization"
Provides-Extra: quantum
Requires-Dist: pyscf>=2.3.0; extra == "quantum"
Requires-Dist: qiskit-nature>=0.7.0; extra == "quantum"
Requires-Dist: pennylane>=0.32.0; extra == "quantum"
Provides-Extra: materials
Requires-Dist: pymatgen>=2024.1.0; extra == "materials"
Requires-Dist: matminer>=0.9.0; extra == "materials"
Requires-Dist: mp-api>=0.41.0; extra == "materials"
Provides-Extra: ml
Requires-Dist: scikit-learn>=1.3.0; extra == "ml"
Requires-Dist: torch>=2.0.0; extra == "ml"
Requires-Dist: transformers>=4.30.0; extra == "ml"
Provides-Extra: dev
Requires-Dist: pytest>=7.0.0; extra == "dev"
Requires-Dist: pytest-asyncio>=0.21.0; extra == "dev"
Requires-Dist: pytest-cov>=4.0.0; extra == "dev"
Requires-Dist: pytest-mock>=3.11.0; extra == "dev"
Requires-Dist: ruff>=0.1.0; extra == "dev"
Requires-Dist: mypy>=1.0.0; extra == "dev"
Requires-Dist: black>=23.0.0; extra == "dev"
Requires-Dist: isort>=5.12.0; extra == "dev"
Requires-Dist: pre-commit>=3.0.0; extra == "dev"
Provides-Extra: docs
Requires-Dist: mkdocs>=1.5.0; extra == "docs"
Requires-Dist: mkdocs-material>=9.0.0; extra == "docs"
Requires-Dist: mkdocstrings[python]>=0.24.0; extra == "docs"
Requires-Dist: mkdocs-jupyter>=0.24.0; extra == "docs"
Provides-Extra: all
Requires-Dist: crystalyse-ai[materials,ml,quantum,visualization]; extra == "all"
